reproduce_crash.py
AnosysLoggers/__init__.py
AnosysLoggers/decorator.py
AnosysLoggers/tracing.py
AnosysLoggers/utils.py
anosys_logger_4_openai-0.0.12.dist-info/licenses/LICENSE
anosys_logger_4_openai-0.0.12.dist-info/METADATA
anosys_logger_4_openai-0.0.12.dist-info/WHEEL
anosys_logger_4_openai-0.0.12.dist-info/top_level.txt
anosys_logger_4_openai-0.0.12.dist-info/RECORD
