Metadata-Version: 2.4
Name: anosys-logger-4-openai
Version: 0.0.12
Summary: A helper package, to support implementation to AnoSys platform easly
Author-email: Moisis Vafeiadis <moisisv@gmail.com>
License: MIT License
Project-URL: Homepage, https://anosys.ai
Requires-Python: <3.13,>=3.9
License-File: LICENSE
Requires-Dist: opentelemetry-api>=1.22.0
Requires-Dist: opentelemetry-sdk>=1.22.0
Requires-Dist: traceai-openai>=0.1.0
Requires-Dist: requests>=2.25.1
Requires-Dist: python-dotenv>=0.21.0
Dynamic: license-file
